MANIFEST.in
README.rst
setup.py
faq/__init__.py
faq/admin.py
faq/cms_app.py
faq/context_processors.py
faq/forms.py
faq/models.py
faq/urls.py
faq/views.py
faq/migrations/0001_initial.py
faq/migrations/0002_auto__chg_field_question_question.py
faq/migrations/__init__.py
faq/templates/faq/index.html
faq/templates/faq/list.html
farm_faq.egg-info/PKG-INFO
farm_faq.egg-info/SOURCES.txt
farm_faq.egg-info/dependency_links.txt
farm_faq.egg-info/not-zip-safe
farm_faq.egg-info/requires.txt
farm_faq.egg-info/top_level.txt