Metadata-Version: 1.1
Name: farm-faq
Version: 0.91
Summary: Provides FAQ implementation
Home-page: UNKNOWN
Author: Jon Atkinson
Author-email: jon@wearefarm.com
License: BSD
Keywords: faq
Platform: UNKNOWN
Classifier: Development Status :: 4 - Beta
Classifier: Environment :: Web Environment
Classifier: Framework :: Django
Classifier: Intended Audience :: Developers
Classifier: License :: OSI Approved :: BSD License
Classifier: Operating System :: OS Independent
Classifier: Programming Language :: Python
